{
	"resourceType":"Conformance",
	"id":"1.0",
	"version":"0.4.0",
	"name":"UPMC Enterprises FHIR POC Conformance Statement",
	"publisher":"UPMC Enterprises",
	"telecom":[
		{
			"system":"phone",
			"value":"1111111111111"
		}
	],
	"description":"his is the conformance statement for the FHIR proof of concept project at UPMC Enterprises",
	"status":"draft",
	"date":"2015-03-30T13:49:54",
	"format":[
		"json"
	],
	"rest":[
		{
			"mode":"server",
			"documentation":"fdafdsafdsafdsaf",
			"resource":[
				{
					"type":"Conformance",
					"profile":{
						"reference":"dfadfsa"
					},
					"interaction":[
						{
							"code":"read"
						},
						{
							"code":"vread"
						}
					],
					"searchParam":[
						{
							"name":"format",
							"definition":"http://hl7.org/fhir/SearchParameter/conformance-format",
							"type":"token",
							"documentation":"formats supported (xml | json | mime type)"
						},
						{
							"name":"format",
							"definition":"http://hl7.org/fhir/SearchParameter/conformance-date",
							"type":"date",
							"documentation":"The conformance statement publication date"
						}
					]
				},
				{
					"type":"Observation",
					"profile":{
						"reference":"dfadfsa"
					},
					"interaction":[
						{
							"code":"read"
						},
						{
							"code":"create"
						}
					],
					"searchParam":[
						{
							"name":"format",
							"definition":"http://hl7.org/fhir/SearchParameter/conformance-format",
							"type":"token",
							"documentation":"formats supported (xml | json | mime type)"
						},
						{
							"name":"format",
							"definition":"http://hl7.org/fhir/SearchParameter/conformance-date",
							"type":"date",
							"documentation":"The conformance statement publication date"
						}
					]
				}
			],
			"operation":[
				{
					"name":"getObservation",
					"definition":{
						"display":"localhost:8080/Observation/{id}"
					}
				}
			]
		}
	]
}